odoo/addons/base_partner_company_group/README.rst
odoo/addons/base_partner_company_group/__init__.py
odoo/addons/base_partner_company_group/__manifest__.py
odoo/addons/base_partner_company_group/i18n/base_partner_company_group.pot
odoo/addons/base_partner_company_group/i18n/ca.po
odoo/addons/base_partner_company_group/i18n/es.po
odoo/addons/base_partner_company_group/i18n/fr.po
odoo/addons/base_partner_company_group/i18n/fr_FR.po
odoo/addons/base_partner_company_group/i18n/hr.po
odoo/addons/base_partner_company_group/i18n/it.po
odoo/addons/base_partner_company_group/i18n/partner_company_group.pot
odoo/addons/base_partner_company_group/i18n/pt_BR.po
odoo/addons/base_partner_company_group/i18n/zh_CN.po
odoo/addons/base_partner_company_group/models/__init__.py
odoo/addons/base_partner_company_group/models/res_partner.py
odoo/addons/base_partner_company_group/readme/CONTRIBUTORS.md
odoo/addons/base_partner_company_group/readme/CREDITS.md
odoo/addons/base_partner_company_group/readme/DESCRIPTION.md
odoo/addons/base_partner_company_group/static/description/icon.png
odoo/addons/base_partner_company_group/static/description/index.html
odoo/addons/base_partner_company_group/tests/__init__.py
odoo/addons/base_partner_company_group/tests/test_base_partner_company_group.py
odoo/addons/base_partner_company_group/views/contact_view.xml
odoo_addon_base_partner_company_group-19.0.1.1.0.5.dist-info/METADATA
odoo_addon_base_partner_company_group-19.0.1.1.0.5.dist-info/WHEEL
odoo_addon_base_partner_company_group-19.0.1.1.0.5.dist-info/top_level.txt
odoo_addon_base_partner_company_group-19.0.1.1.0.5.dist-info/RECORD
