Metadata-Version: 2.1
Name: odoo-addon-base_partner_company_group
Version: 19.0.1.1.0.5
Requires-Dist: odoo==19.0.*
Summary: Adds the possibility to add a company group to a company
Home-page: https://github.com/OCA/partner-contact
License: AGPL-3
Author: Camptocamp, Odoo Community Association (OCA)
Author-email: support@odoo-community.org
Classifier: Programming Language :: Python
Classifier: Framework :: Odoo
Classifier: Framework :: Odoo :: 19.0
Classifier: License :: OSI Approved :: GNU Affero General Public License v3
